languageassistant/__init__.py
languageassistant/agents/__init__.py
languageassistant/agents/conversation/__init__.py
languageassistant/agents/conversation/agent.py
languageassistant/agents/conversation/base.py
languageassistant/agents/conversation/loader.py
languageassistant/agents/planner/__init__.py
languageassistant/agents/planner/agent.py
languageassistant/agents/planner/base.py
languageassistant/agents/planner/loader.py
languageassistant/agents/planner/schema.py
languageassistant/assistant.py
languageassistant/py.typed
languageassistant/transcriber.py
languageassistant/tts.py
languageassistant/utils.py
languageassistant-0.1.0.dist-info/METADATA
languageassistant-0.1.0.dist-info/WHEEL
languageassistant-0.1.0.dist-info/RECORD
