Metadata-Version: 2.1
Name: languageassistant
Version: 0.1.0
Summary: An LLM-powered language learning assistant
Home-page: https://dagleaves.github.io/languageassistant
License: MIT
Author: Daniel Gleaves
Author-email: daniel@dagleaves.com
Requires-Python: >=3.9,<3.11
Classifier: Development Status :: 4 - Beta
Classifier: Intended Audience :: Developers
Classifier: License :: OSI Approved :: MIT License
Classifier: Operating System :: OS Independent
Classifier: Programming Language :: Python
Classifier: Programming Language :: Python :: 3
Classifier: Programming Language :: Python :: 3.9
Classifier: Programming Language :: Python :: 3.10
Classifier: Programming Language :: Python :: 3.8
Classifier: Topic :: Software Development :: Libraries :: Python Modules
Classifier: Typing :: Typed
Requires-Dist: faiss-cpu (>=1.7.4,<2.0.0)
Requires-Dist: google-cloud-texttospeech (>=2.14.1,<3.0.0)
Requires-Dist: langchain (>=0.0.162,<0.0.163)
Requires-Dist: lark (>=1.1.5,<2.0.0)
Requires-Dist: openai (>=0.27.6,<0.28.0)
Requires-Dist: pyaudio (>=0.2.13,<0.3.0)
Requires-Dist: pydub (>=0.25.1,<0.26.0)
Requires-Dist: questionary (>=1.10.0,<2.0.0)
Requires-Dist: speechrecognition (>=3.10.0,<4.0.0)
Requires-Dist: tiktoken (>=0.4.0,<0.5.0)
Requires-Dist: toml (>=0.10.2,<0.11.0)
Project-URL: Documentation, https://dagleaves.github.io/languageassistant
Project-URL: Repository, https://github.com/dagleaves/languageassistant
